referencing_loaders/__init__.py
referencing_loaders/py.typed
referencing_loaders/tests/__init__.py
referencing_loaders/tests/test_loaders.py
referencing_loaders-2025.1.1.dist-info/METADATA
referencing_loaders-2025.1.1.dist-info/WHEEL
referencing_loaders-2025.1.1.dist-info/licenses/COPYING
referencing_loaders-2025.1.1.dist-info/RECORD
