Metadata-Version: 2.4
Name: referencing-loaders
Version: 2025.1.1
Summary: Loading resources from various locations into referencing registries
Project-URL: Homepage, https://github.com/python-jsonschema/referencing-loaders
Project-URL: Issues, https://github.com/python-jsonschema/referencing-loaders/issues/
Project-URL: Funding, https://github.com/sponsors/Julian
Project-URL: Source, https://github.com/python-jsonschema/referencing-loaders
Author-email: Julian Berman <Julian+referencing-loaders@GrayVines.com>
License-Expression: MIT
License-File: COPYING
Keywords: asyncapi,json,jsonschema,openapi,referencing
Classifier: Development Status :: 4 - Beta
Classifier: Intended Audience :: Developers
Classifier: Operating System :: OS Independent
Classifier: Programming Language :: Python
Classifier: Programming Language :: Python :: 3.9
Classifier: Programming Language :: Python :: 3.10
Classifier: Programming Language :: Python :: 3.11
Classifier: Programming Language :: Python :: 3.12
Classifier: Programming Language :: Python :: 3.13
Classifier: Programming Language :: Python :: Implementation :: CPython
Classifier: Programming Language :: Python :: Implementation :: PyPy
Classifier: Topic :: File Formats :: JSON
Classifier: Topic :: File Formats :: JSON :: JSON Schema
Requires-Python: >=3.9
Requires-Dist: referencing>=0.32.0
